badoo/__init__.py
badoo/badoo.py
badoo/cli.py
badoo/notes.py
tests/__init__.py
tests/test_badoo.py
badoo-1.7.1.dist-info/AUTHORS.rst
badoo-1.7.1.dist-info/LICENSE
badoo-1.7.1.dist-info/METADATA
badoo-1.7.1.dist-info/WHEEL
badoo-1.7.1.dist-info/entry_points.txt
badoo-1.7.1.dist-info/top_level.txt
badoo-1.7.1.dist-info/RECORD
