Metadata-Version: 2.1
Name: badoo
Version: 1.7.1
Summary: remotely control badoo
Home-page: https://github.com/matttsb/badoo
Author: Matt Burke
Author-email: matttsburke@gmail.com
License: GNU General Public License v3
Keywords: badoo
Platform: UNKNOWN
Classifier: Development Status :: 5 - Production/Stable
Classifier: Intended Audience :: Developers
Classifier: License :: OSI Approved :: GNU General Public License v3 (GPLv3)
Classifier: Natural Language :: English
Classifier: Programming Language :: Python :: 3
Classifier: Programming Language :: Python :: 3.5
Classifier: Programming Language :: Python :: 3.6
Classifier: Programming Language :: Python :: 3.7
Classifier: Programming Language :: Python :: 3.8
Requires-Python: >=3.5
Requires-Dist: Click (>=7.0)
Requires-Dist: selenium
Requires-Dist: BeautifulSoup4
Requires-Dist: lxml
Requires-Dist: Pillow
